riaesc/__init__.py
riaesc/socks.py
riaesc-1.0.0.dist-info/LICENSE
riaesc-1.0.0.dist-info/METADATA
riaesc-1.0.0.dist-info/WHEEL
riaesc-1.0.0.dist-info/RECORD
