Metadata-Version: 2.3
Name: riaesc
Version: 1.0.0
Summary: Async SOCKS5 proxy library for Pyrogram and Hydrogram - Zero dependency, high performance
License: MIT
Keywords: socks,proxy,pyrogram,hydrogram,telegram,async,mtproto
Author: riaesc
Author-email: riaesc@example.com
Requires-Python: >=3.11,<4.0
Classifier: Development Status :: 5 - Production/Stable
Classifier: Framework :: AsyncIO
Classifier: Intended Audience :: Developers
Classifier: License :: OSI Approved :: MIT License
Classifier: Operating System :: OS Independent
Classifier: Programming Language :: Python :: 3
Classifier: Programming Language :: Python :: 3.11
Classifier: Programming Language :: Python :: 3.12
Classifier: Programming Language :: Python :: 3.13
Classifier: Topic :: Internet :: Proxy Servers
Classifier: Topic :: Software Development :: Libraries :: Python Modules
Requires-Dist: requests (>=2.32.5,<3.0.0)
Project-URL: Bug Tracker, https://github.com/yourusername/riaesc/issues
Project-URL: Documentation, https://github.com/yourusername/riaesc
Project-URL: Homepage, https://github.com/yourusername/riaesc
Project-URL: Repository, https://github.com/yourusername/riaesc
